adminutilities/__init__.py
adminutilities/admin.py
adminutilities/apps.py
adminutilities/decorators.py
adminutilities/middleware.py
adminutilities/urls.py
adminutilities/utils.py
adminutilities/views.py
adminutilities/management/__init__.py
adminutilities/management/commands/__init__.py
adminutilities/management/commands/adminutilities.py
adminutilities/templates/admin/index.html
adminutilities/templates/adminutilities/admin/customfunction_form.html
django_adminutilities-0.1.7.dist-info/AUTHORS.rst
django_adminutilities-0.1.7.dist-info/LICENSE
django_adminutilities-0.1.7.dist-info/METADATA
django_adminutilities-0.1.7.dist-info/WHEEL
django_adminutilities-0.1.7.dist-info/top_level.txt
django_adminutilities-0.1.7.dist-info/RECORD
