Metadata-Version: 2.1
Name: django-adminutilities
Version: 0.1.7
Summary: Allow calling registered custom functions (system tools, script functions, etc.)  via admin UI or manage.py command.
Home-page: https://github.com/Skylor-Tang/django-adminutilities
Author: tangmeijian
Author-email: tang1996mei@gmail.com
License: BSD license
Keywords: django,utilities,admin
Classifier: Development Status :: 2 - Pre-Alpha
Classifier: Intended Audience :: Developers
Classifier: License :: OSI Approved :: BSD License
Classifier: Natural Language :: English
Classifier: Programming Language :: Python :: 3
Classifier: Programming Language :: Python :: 3.6
Classifier: Programming Language :: Python :: 3.7
Classifier: Programming Language :: Python :: 3.8
Classifier: Programming Language :: Python :: 3.9
Classifier: Programming Language :: Python :: 3.10
Requires-Python: >=3.6
License-File: LICENSE
License-File: AUTHORS.rst
